README.md
setup.py
authone/__init__.py
authone/config.py
authone/core.py
authone/error.py
authone/http_client.py
authone/response.py
authone/version.py
authone/resources/__init__.py
authone/resources/base.py
authone/resources/token.py
authone/resources/user.py
authone/utils/__init__.py
authone/utils/did_token.py
authone/utils/http.py
authone/utils/time.py
authone_admin.egg-info/PKG-INFO
authone_admin.egg-info/SOURCES.txt
authone_admin.egg-info/dependency_links.txt
authone_admin.egg-info/not-zip-safe
authone_admin.egg-info/requires.txt
authone_admin.egg-info/top_level.txt