Metadata-Version: 2.1
Name: authone-admin
Version: 0.0.2
Summary: AuthOne Python Library
Home-page: https://github.com/Generative-Labs/AuthOne-Python
Author: AuthOne
Author-email: AuthOne@housechan.com
License: MIT
Project-URL: Website, https://github.com/Generative-Labs/AuthOne-Python
Keywords: AuthOne python sdk
Platform: UNKNOWN
Classifier: Development Status :: 3 - Alpha
Classifier: Programming Language :: Python
Classifier: Programming Language :: Python :: 3.6
Classifier: Intended Audience :: Developers
Classifier: License :: OSI Approved :: MIT License
Classifier: Operating System :: OS Independent
Requires-Python: >=3.6
